digitz/__about__.py
digitz/__init__.py
digitz/enums.py
digitz/phonenumbers.py
digitz-0.8.0.dist-info/METADATA
digitz-0.8.0.dist-info/WHEEL
digitz-0.8.0.dist-info/licenses/LICENSE.txt
digitz-0.8.0.dist-info/RECORD
