Metadata-Version: 2.4
Name: digitz
Version: 0.8.0
Summary: Python phone numbers made easy.
Project-URL: Documentation, https://digitz.rykroon.com
Project-URL: Source, https://github.com/rykroon/digitz
Project-URL: Issues, https://github.com/rykroon/digitz/issues
Author-email: Ryan Kroon <rykroon.tech@gmail.com>
License-Expression: MIT
License-File: LICENSE.txt
Keywords: number,numbers,phone,phone number,phone numbers,phonenumber,phonenumbers
Classifier: Programming Language :: Python
Classifier: Programming Language :: Python :: 3.10
Classifier: Programming Language :: Python :: 3.11
Classifier: Programming Language :: Python :: 3.12
Classifier: Programming Language :: Python :: 3.13
Classifier: Programming Language :: Python :: 3.14
Classifier: Programming Language :: Python :: Implementation :: CPython
Requires-Python: >=3.10
Requires-Dist: phonenumbers==9.*
